test_10_powerhouse_helper/__init__.py
test_10_powerhouse_helper/main.py
test_10_powerhouse_helper/AddressBook/Address_Book_Handler.py
test_10_powerhouse_helper/AddressBook/addressbook.py
test_10_powerhouse_helper/AddressBook/addressbook_data.py
test_10_powerhouse_helper/NoteBook/Note.py
test_10_powerhouse_helper/NoteBook/Note_Book_Handler.py
test_10_powerhouse_helper/OtherModules/Sort_Files.py
test_10_powerhouse_helper/OtherModules/Сalculator.py
venv/Lib/site-packages/_distutils_hack/__init__.py
venv/Lib/site-packages/_distutils_hack/override.py
venv/Lib/site-packages/build/__init__.py
venv/Lib/site-packages/build/__main__.py
venv/Lib/site-packages/build/env.py
venv/Lib/site-packages/build/util.py
venv/Lib/site-packages/colorama/__init__.py
venv/Lib/site-packages/colorama/ansi.py
venv/Lib/site-packages/colorama/ansitowin32.py
venv/Lib/site-packages/colorama/initialise.py
venv/Lib/site-packages/colorama/win32.py
venv/Lib/site-packages/colorama/winterm.py
venv/Lib/site-packages/colorama/tests/__init__.py
venv/Lib/site-packages/colorama/tests/ansi_test.py
venv/Lib/site-packages/colorama/tests/ansitowin32_test.py
venv/Lib/site-packages/colorama/tests/initialise_test.py
venv/Lib/site-packages/colorama/tests/isatty_test.py
venv/Lib/site-packages/colorama/tests/utils.py
venv/Lib/site-packages/colorama/tests/winterm_test.py
venv/Lib/site-packages/packaging/__init__.py
venv/Lib/site-packages/packaging/_elffile.py
venv/Lib/site-packages/packaging/_manylinux.py
venv/Lib/site-packages/packaging/_musllinux.py
venv/Lib/site-packages/packaging/_parser.py
venv/Lib/site-packages/packaging/_structures.py
venv/Lib/site-packages/packaging/_tokenizer.py
venv/Lib/site-packages/packaging/markers.py
venv/Lib/site-packages/packaging/requirements.py
venv/Lib/site-packages/packaging/specifiers.py
venv/Lib/site-packages/packaging/tags.py
venv/Lib/site-packages/packaging/utils.py
venv/Lib/site-packages/packaging/version.py
venv/Lib/site-packages/pip/__init__.py
test_10_powerhouse_helper-1.dist-info/LICENSE
test_10_powerhouse_helper-1.dist-info/METADATA
test_10_powerhouse_helper-1.dist-info/WHEEL
test_10_powerhouse_helper-1.dist-info/entry_points.txt
test_10_powerhouse_helper-1.dist-info/top_level.txt
test_10_powerhouse_helper-1.dist-info/RECORD
